git_river/__init__.py
git_river/__main__.py
git_river/cli.py
git_river/commands/__init__.py
git_river/commands/clone.py
git_river/commands/config.py
git_river/commands/forge.py
git_river/commands/repo.py
git_river/config.py
git_river/ext/__init__.py
git_river/ext/click.py
git_river/ext/gitlab.py
git_river/forge.py
git_river/repository.py
git_river/tests/__init__.py
git_river/tests/test_config.py
git_river/tests/test_git.py
git_river-1.4.0.dist-info/entry_points.txt
git_river-1.4.0.dist-info/LICENSE
git_river-1.4.0.dist-info/WHEEL
git_river-1.4.0.dist-info/METADATA
git_river-1.4.0.dist-info/RECORD
