Metadata-Version: 2.1
Name: git-river
Version: 1.4.0
Summary: Tools for working with upstream repositories
Home-page: https://pypi.org/project/git-river/
License: MPL-2.0
Author: Sam Clements
Author-email: sclements@datto.com
Requires-Python: >=3.9,<4.0
Classifier: Development Status :: 5 - Production/Stable
Classifier: Environment :: Console
Classifier: License :: OSI Approved
Classifier: License :: OSI Approved :: Mozilla Public License 2.0 (MPL 2.0)
Classifier: Programming Language :: Python :: 3
Classifier: Programming Language :: Python :: 3.10
Classifier: Programming Language :: Python :: 3.9
Classifier: Topic :: Software Development
Classifier: Topic :: Software Development :: Version Control
Classifier: Topic :: Software Development :: Version Control :: Git
Requires-Dist: GitPython (>=3.1.27,<4.0.0)
Requires-Dist: PyGithub (>=1.55,<2.0)
Requires-Dist: appdirs (>=1.4.4,<2.0.0)
Requires-Dist: click (>=8.0.4,<9.0.0)
Requires-Dist: colorama (>=0.4.4,<0.5.0)
Requires-Dist: giturlparse (>=0.10.0,<0.11.0)
Requires-Dist: inflect (>=5.4.0,<6.0.0)
Requires-Dist: pydantic (>=1.9.0,<2.0.0)
Requires-Dist: python-gitlab (>=3.2.0,<4.0.0)
Requires-Dist: structlog (>=21.5.0,<22.0.0)
Project-URL: Repository, https://github.com/datto/git-river
